dtmapi/__init__.py
dtmapi/api.py
dtmapi/config.py
dtmapi/exceptions.py
dtmapi/validators.py
dtmapi/version.py
dtmapi-0.1.8.dist-info/licenses/LICENSE
tests/__init__.py
tests/test_api.py
tests/test_exceptions.py
tests/test_validators.py
dtmapi-0.1.8.dist-info/METADATA
dtmapi-0.1.8.dist-info/WHEEL
dtmapi-0.1.8.dist-info/top_level.txt
dtmapi-0.1.8.dist-info/RECORD
