Metadata-Version: 2.4
Name: dtmapi
Version: 0.1.8
Summary: A Python package for fetching data from the IOM's Displacement Tracking Matrix (DTM).
Home-page: https://github.com/Displacement-Tracking-Matrix/dtmapi
Author: Luong Bang Tran
Author-email: lutran@iom.int
License: MIT
Project-URL: Github, https://github.com/Displacement-Tracking-Matrix/dtmapi
Project-URL: Documentation, https://dtmapi.readthedocs.io/en/latest/
Keywords: dtm,displacement,tracking,matrix,iom,idp,humanitarian,migration,refugees
Classifier: Development Status :: 4 - Beta
Classifier: Intended Audience :: Developers
Classifier: Intended Audience :: Science/Research
Classifier: Topic :: Scientific/Engineering
Classifier: Topic :: Sociology
Classifier: Programming Language :: Python :: 3
Classifier: Programming Language :: Python :: 3.8
Classifier: Programming Language :: Python :: 3.9
Classifier: Programming Language :: Python :: 3.10
Classifier: Programming Language :: Python :: 3.11
Classifier: Programming Language :: Python :: 3.12
Classifier: License :: OSI Approved :: MIT License
Classifier: Operating System :: OS Independent
Requires-Python: >=3.8
License-File: LICENSE
Requires-Dist: requests>=2.31.0
Requires-Dist: pandas>=2.0.0
Requires-Dist: openpyxl>=3.1.0
Provides-Extra: test
Requires-Dist: pytest>=9.0.0; extra == "test"
Requires-Dist: pytest-cov>=7.0.0; extra == "test"
Requires-Dist: pytest-mock>=3.15.1; extra == "test"
Provides-Extra: docs
Requires-Dist: sphinx>=7.0.0; extra == "docs"
Requires-Dist: sphinx-rtd-theme>=2.0.0; extra == "docs"
Provides-Extra: dev
Requires-Dist: ipykernel>=7.1.0; extra == "dev"
Dynamic: author
Dynamic: author-email
Dynamic: classifier
Dynamic: description
Dynamic: description-content-type
Dynamic: home-page
Dynamic: keywords
Dynamic: license
Dynamic: license-file
Dynamic: project-url
Dynamic: provides-extra
Dynamic: requires-dist
Dynamic: requires-python
Dynamic: summary
